offlineyoutube/__init__.py
offlineyoutube/app.py
offlineyoutube/config.py
offlineyoutube/lib/__init__.py
offlineyoutube/lib/functions.py
offlineyoutube-2.1.9.dist-info/LICENSE
offlineyoutube-2.1.9.dist-info/METADATA
offlineyoutube-2.1.9.dist-info/WHEEL
offlineyoutube-2.1.9.dist-info/entry_points.txt
offlineyoutube-2.1.9.dist-info/top_level.txt
offlineyoutube-2.1.9.dist-info/RECORD
