Metadata-Version: 2.1
Name: offlineyoutube
Version: 2.1.9
Summary: A YouTube video search and management tool with a Gradio interface
Home-page: https://github.com/DrewThomasson/offlineYoutube
Author: Andrew Phillip Thomasson
Author-email: drew.thomasson100@gmail.com
Classifier: Programming Language :: Python :: 3
Classifier: License :: OSI Approved :: MIT License
Classifier: Operating System :: OS Independent
Requires-Python: >=3.8
License-File: LICENSE
Requires-Dist: yt-dlp
Requires-Dist: pandas
Requires-Dist: numpy
Requires-Dist: requests
Requires-Dist: faiss-cpu
Requires-Dist: faster-whisper
Requires-Dist: sentence-transformers
Requires-Dist: gradio==3.36.1
Requires-Dist: argparse
Requires-Dist: beautifulsoup4
Requires-Dist: pysrt
Requires-Dist: webvtt-py
